aspire/__init__.py
aspire/__main__.py
aspire/config_default.yaml
aspire/exceptions.py
aspire/logging.conf
aspire/abinitio/J_sync.py
aspire/abinitio/__init__.py
aspire/abinitio/commonline_base.cu
aspire/abinitio/commonline_base.py
aspire/abinitio/commonline_c2.py
aspire/abinitio/commonline_c3_c4.py
aspire/abinitio/commonline_cn.py
aspire/abinitio/commonline_d2.py
aspire/abinitio/commonline_ev.py
aspire/abinitio/commonline_gcar.py
aspire/abinitio/commonline_irls.py
aspire/abinitio/commonline_lud.py
aspire/abinitio/commonline_sdp.py
aspire/abinitio/commonline_sync.py
aspire/abinitio/commonline_sync3n.cu
aspire/abinitio/commonline_sync3n.py
aspire/abinitio/commonline_utils.py
aspire/abinitio/sync_voting.py
aspire/apple/__init__.py
aspire/apple/apple.py
aspire/apple/helper.py
aspire/apple/picking.py
aspire/basis/__init__.py
aspire/basis/basis.py
aspire/basis/basis_utils.py
aspire/basis/dirac.py
aspire/basis/fb.py
aspire/basis/fb_2d.py
aspire/basis/fb_3d.py
aspire/basis/ffb_2d.py
aspire/basis/ffb_3d.py
aspire/basis/fle_2d.py
aspire/basis/fle_2d_utils.py
aspire/basis/fpswf_2d.py
aspire/basis/fpswf_3d.py
aspire/basis/fspca.py
aspire/basis/pswf_2d.py
aspire/basis/pswf_3d.py
aspire/basis/pswf_utils.py
aspire/basis/steerable.py
aspire/classification/__init__.py
aspire/classification/averager2d.py
aspire/classification/class2d.py
aspire/classification/class_selection.py
aspire/classification/legacy_implementations.py
aspire/classification/reddy_chatterji.py
aspire/classification/rir_class2d.py
aspire/commands/__init__.py
aspire/commands/_config.py
aspire/commands/apple.py
aspire/commands/cov3d.py
aspire/commands/denoise.py
aspire/commands/estimate_ctf.py
aspire/commands/extract_particles.py
aspire/commands/orient3d.py
aspire/commands/preprocess.py
aspire/covariance/__init__.py
aspire/covariance/covar.py
aspire/covariance/covar2d.py
aspire/ctf/__init__.py
aspire/ctf/ctf_estimator.py
aspire/denoising/__init__.py
aspire/denoising/adaptive_support.py
aspire/denoising/class_avg.py
aspire-0.14.2.dist-info/licenses/LICENSE
aspire-0.14.2.dist-info/METADATA
aspire-0.14.2.dist-info/WHEEL
aspire-0.14.2.dist-info/entry_points.txt
aspire-0.14.2.dist-info/top_level.txt
aspire-0.14.2.dist-info/RECORD
