Metadata-Version: 2.4
Name: aspire
Version: 0.14.2
Summary: Algorithms for Single Particle Reconstruction
Author: Joakim Anden, Vineet Bansal, Josh Carmichael, Chris Langfield, Ayelet Heimowitz, Yoel Shkolnisky, Amit Singer, Kris Sowattanangkul, Garrett Wright, Junchao Xia
Maintainer-email: ASPIRE Developers <ASPIRE-DEVS@princeton.edu>
License-Expression: GPL-3.0-only
Project-URL: Homepage, http://spr.math.princeton.edu/
Project-URL: Bug Reports, https://github.com/ComputationalCryoEM/ASPIRE-Python/issues
Project-URL: Source, https://github.com/ComputationalCryoEM/ASPIRE-Python
Classifier: Development Status :: 3 - Alpha
Classifier: Programming Language :: Python
Requires-Python: >=3.9
License-File: LICENSE
Requires-Dist: click
Requires-Dist: confuse>=2.0.0
Requires-Dist: cvxpy
Requires-Dist: finufft==2.4.0; sys_platform != "darwin"
Requires-Dist: finufft==2.3.0; sys_platform == "darwin"
Requires-Dist: gemmi>=0.6.5
Requires-Dist: joblib
Requires-Dist: matplotlib>=3.2.0
Requires-Dist: mrcfile
Requires-Dist: numpy>=1.25.0
Requires-Dist: packaging
Requires-Dist: pooch>=1.7.0
Requires-Dist: pillow
Requires-Dist: psutil
Requires-Dist: pymanopt
Requires-Dist: PyWavelets
Requires-Dist: scipy>=1.10.0
Requires-Dist: scikit-learn>=1.5.0
Requires-Dist: scikit-image
Requires-Dist: setuptools>=0.41
Requires-Dist: tqdm
Provides-Extra: gpu-12x
Requires-Dist: cupy-cuda12x; extra == "gpu-12x"
Requires-Dist: cufinufft==2.4.0; extra == "gpu-12x"
Provides-Extra: dev
Requires-Dist: black; extra == "dev"
Requires-Dist: bumpversion; extra == "dev"
Requires-Dist: check-manifest; extra == "dev"
Requires-Dist: flake8>=3.7.0; extra == "dev"
Requires-Dist: isort; extra == "dev"
Requires-Dist: jupyter; extra == "dev"
Requires-Dist: pooch; extra == "dev"
Requires-Dist: pyflakes; extra == "dev"
Requires-Dist: pydocstyle; extra == "dev"
Requires-Dist: pytest; extra == "dev"
Requires-Dist: pytest-cov; extra == "dev"
Requires-Dist: pytest-random-order; extra == "dev"
Requires-Dist: pytest-xdist; extra == "dev"
Requires-Dist: requests; extra == "dev"
Requires-Dist: sphinxcontrib-bibtex; extra == "dev"
Requires-Dist: sphinxcontrib-mermaid; extra == "dev"
Requires-Dist: sphinx-gallery; extra == "dev"
Requires-Dist: sphinx-rtd-theme>=0.4.2; extra == "dev"
Requires-Dist: snakeviz; extra == "dev"
Requires-Dist: tox; extra == "dev"
Requires-Dist: twine; extra == "dev"
Dynamic: license-file
